eparams/__init__.py
eparams/constraints.py
eparams/eloader.py
eparams/main.py
eparams-0.2.dist-info/METADATA
eparams-0.2.dist-info/WHEEL
eparams-0.2.dist-info/top_level.txt
eparams-0.2.dist-info/RECORD
