Metadata-Version: 2.1
Name: eparams
Version: 0.2
Summary: Parameter class for all
Home-page: https://github.com/amirfru/eparams
Author: Amir Fruchtman
Author-email: amir.fru@gmail.com
Keywords: params,config,development
Classifier: Development Status :: 3 - Alpha
Classifier: Intended Audience :: Developers
Classifier: Topic :: Software Development
Classifier: License :: OSI Approved :: The Unlicense (Unlicense)
Classifier: Programming Language :: Python :: 3
Classifier: Programming Language :: Python :: 3.6
Classifier: Programming Language :: Python :: 3.7
Classifier: Programming Language :: Python :: 3.8
Classifier: Programming Language :: Python :: 3.9
Classifier: Programming Language :: Python :: 3.10
Requires-Python: >=3.6, <4
Requires-Dist: typeguard
